pymedphys_pinnacle/__init__.py
pymedphys_pinnacle/_install_requires.py
pymedphys_pinnacle/_version.py
pymedphys_pinnacle/export/__init__.py
pymedphys_pinnacle/export/constants.py
pymedphys_pinnacle/export/image.py
pymedphys_pinnacle/export/pinn_yaml.py
pymedphys_pinnacle/export/pinnacle.py
pymedphys_pinnacle/export/pinnacle_cli.py
pymedphys_pinnacle/export/pinnacle_image.py
pymedphys_pinnacle/export/pinnacle_plan.py
pymedphys_pinnacle/export/rtdose.py
pymedphys_pinnacle/export/rtplan.py
pymedphys_pinnacle/export/rtstruct.py
pymedphys_pinnacle-0.11.0.dist-info/LICENSE-AGPL-3.0-or-later
pymedphys_pinnacle-0.11.0.dist-info/LICENSE-MIT
pymedphys_pinnacle-0.11.0.dist-info/METADATA
pymedphys_pinnacle-0.11.0.dist-info/WHEEL
pymedphys_pinnacle-0.11.0.dist-info/top_level.txt
pymedphys_pinnacle-0.11.0.dist-info/RECORD
